{"noMoreComments": true, "cursorEnd": 0, "id": "6666904", "comments": [{"postBy": {"location": "\u9ad8\u96c4\u5e02\u00b7\u53f0\u7063", "utc": 1505933149000, "level": 0, "avatar": "http://filestoresg1.beetalkmobile.com:8081/file/-5990959578923799860", "name": "\u741b"}, "content": "\u597d\u50cf\u5f88\u5229\u5bb3\uff01", "urls": [], "replies": {"first": [{"content": "\u600e\u6a23\u53b2\u5bb3", "reply": "", "id": 48641040, "name": "BeeTalk User"}, {"content": "\u5c0d\u73a9\u5f88\u53b2\u5bb3", "reply": "", "id": 48689267, "name": "\u741b"}], "last": [], "noMoreReplies": true}, "images": [], "id": 72271380}, {"postBy": {"location": "\u53f0\u7063", "utc": 1505972257000, "level": 0, "avatar": "http://filestoresg1.beetalkmobile.com:8081/file/9058702600949922839", "name": "\u53db\u53db"}, "content": "\u53b2\u5bb3\u53b2\u5bb3  \u8eab\u7d93\u767e\u6230", "urls": [], "replies": {"first": [], "last": [], "noMoreReplies": true}, "images": [], "id": 72290134}, {"postBy": {"location": "\u65b0\u5317\u5e02\u00b7\u53f0\u7063", "utc": 1506063036000, "level": 0, "avatar": "http://filestoresg1.beetalkmobile.com:8081/file/8998307521366742150", "name": "\u963f\u5f37"}, "content": "\u90a3\u500b\u6253\u5341\u500b\u7684\u55ce\uff1f\u9084\u662f\u8aaa\u90a3\u662f\u8449\u554f\uff1f", "urls": [], "replies": {"first": [], "last": [], "noMoreReplies": true}, "images": [], "id": 72352709}, {"postBy": {"location": "\u53f0\u5317\u5e02\u00b7\u53f0\u7063", "utc": 1506444754000, "level": 0, "avatar": "http://filestoresg1.beetalkmobile.com:8081/file/3316191942378175979", "name": "MR.RIGHT"}, "content": "\u6c92\u5370\u8c61\u2026\u7528\u4e864,5\u5e74\u2026", "urls": [], "replies": {"first": [], "last": [], "noMoreReplies": true}, "images": [], "id": 72647300}, {"postBy": {"location": "\u65b0\u7af9\u5e02\u00b7\u53f0\u7063", "utc": 1506624548000, "level": 0, "avatar": "http://filestoresg1.beetalkmobile.com:8081/file/-1596789941914887213", "name": "Richard"}, "content": "\u4f86\u8a8d\u8b58\u5440", "urls": [], "replies": {"first": [], "last": [], "noMoreReplies": true}, "images": [], "id": 72798823}, {"postBy": {"location": "\u6843\u5712\u5e02\u00b7\u53f0\u7063", "utc": 1506701674000, "level": 0, "avatar": "http://filestoresg1.beetalkmobile.com:8081/file/7209034872397423286", "name": "Ben"}, "content": "\u6240\u4ee5\u5c31\u662f\u7d04\u55ce\uff1f\u771f\u7684\u7d04\u5230\u6688\u8239\u5f88\u96e3\u904e\u54ea \u6628\u5929\u525b\u525b\u7d50\u675f\u7684\u6211 \u771f\u662f\u58de\u7537\u4eba", "urls": [], "replies": {"first": [], "last": [], "noMoreReplies": true}, "images": [], "id": 72864984}, {"postBy": {"location": "\u65b0\u5317\u5e02\u00b7\u53f0\u7063", "utc": 1506828221000, "level": 0, "avatar": "http://filestoresg1.beetalkmobile.com:8081/file/-7284191942686153984", "name": "Ronald_hou"}, "content": "\u600e\u9ebc\u52a0\u4f60\u3001\u611f\u89ba\u5f88\u53b2\u5bb3\u7684\u6a23\u5b50", "urls": [], "replies": {"first": [], "last": [], "noMoreReplies": true}, "images": [], "id": 72965788}, {"postBy": {"location": "", "utc": 1506833594000, "level": 0, "avatar": "http://filestoresg1.beetalkmobile.com:8081/file/525691925933533952", "name": "Marco"}, "content": "\u904e\u53bb\u7684\u4e8b\u904e\u4e86\u5c31\u597d \u4eba\u90fd\u8981\u5411\u524d\u770b \u5225\u4eba\u7684\u8a71\u90fd\u62ff\u4f86\u53c3\u8003\u5c31\u597d \u65e2\u7136\u6539\u8b8a\u4e86 \u90a3\u5c31\u52aa\u529b\u505a\u7d66\u90a3\u4e9b\u77a7\u4e0d\u8d77\u59b3 \u8a0e\u53ad\u59b3\u7684\u4eba\u770b \u8b93\u4ed6\u5011\u901a\u901a\u9589\u5634\ud83e\udd10 \u6211\u77e5\u9053\u904e\u7a0b\u6703\u5f88\u8f9b\u82e6 \u90a3\u4e9b\u82e6\u6211\u90fd\u61c2 \u4f46\u6211\u76f8\u4fe1\u59b3\u53ef\u4ee5\u7684 \u52a0\u6cb9\u54e6\ud83d\udc4a\ud83c\udffb", "urls": [], "replies": {"first": [], "last": [], "noMoreReplies": true}, "images": [], "id": 72970884}, {"postBy": {"location": "\u53f0\u4e2d\u5e02\u00b7\u53f0\u7063", "utc": 1507065534000, "level": 0, "avatar": "http://filestoresg1.beetalkmobile.com:8081/file/-9073652628884301824", "name": "Wei"}, "content": "\u53ef\u4ee5\u52a0\u597d\u53cb\u804a\u5929\u7576\u670b\u53cb\u55ce\uff1f", "urls": [], "replies": {"first": [], "last": [], "noMoreReplies": true}, "images": [], "id": 73178035}, {"postBy": {"location": "\u53f0\u4e2d\u5e02\u00b7\u53f0\u7063", "utc": 1507133898000, "level": 0, "avatar": "http://filestoresg1.beetalkmobile.com:8081/file/1", "name": "Kevin"}, "content": "\u4e0d\u61c2 \u7b2c\u4e00\u5929\u73a9", "urls": [], "replies": {"first": [], "last": [], "noMoreReplies": true}, "images": [], "id": 73237498}, {"postBy": {"location": "", "utc": 1507135876000, "level": 0, "avatar": "http://filestoresg1.beetalkmobile.com:8081/file/7117961204911458360", "name": "\u4e00\u6643\u5c31\u8001\u4e86\ud83d\udeac"}, "content": "\u6c92<br /><br />\ud83d\udc42<br /><br />\u904e<br /><br />\u8036<br /><br />\ud83d\ude2a<br /><br />\ud83d\ude34", "urls": [], "replies": {"first": [], "last": [], "noMoreReplies": true}, "images": [], "id": 73239614}, {"postBy": {"location": "\u53f0\u5317\u5e02\u00b7\u53f0\u7063", "utc": 1507149285000, "level": 0, "avatar": "http://filestoresg1.beetalkmobile.com:8081/file/-9197263747743006596", "name": "Mick "}, "content": "\u6240\u4ee5\u662f\u4ec0\u9ebc\uff1f", "urls": [], "replies": {"first": [], "last": [], "noMoreReplies": true}, "images": [], "id": 73247111}, {"postBy": {"location": "", "utc": 1507301826000, "level": 0, "avatar": "http://filestoresg1.beetalkmobile.com:8081/file/-299099041993670117", "name": "AR"}, "content": "\u70ba\u4ec0\u9ebc\u770b\u6210\u5abd\u5abd@@", "urls": [], "replies": {"first": [], "last": [], "noMoreReplies": true}, "images": [], "id": 73360412}, {"postBy": {"location": "\u9ad8\u96c4\u5e02\u00b7\u53f0\u7063", "utc": 1507309273000, "level": 0, "avatar": "http://filestoresg1.beetalkmobile.com:8081/file/933025799181855046", "name": "\u5fc3\u5bc2\u2618\u4e0d\u5982\u4e0d\u898b"}, "content": "\u5361\u4e00\u500b\uff0c\u7b49\u81c9\u66f8", "urls": [], "replies": {"first": [], "last": [], "noMoreReplies": true}, "images": [], "id": 73368526}, {"postBy": {"location": "", "utc": 1507309384000, "level": 0, "avatar": "http://filestoresg1.beetalkmobile.com:8081/file/4250791134525679783", "name": "\u4e0a\u5e1d\u4fdd\u7950\u4f60"}, "content": "\u53ef\u4ee5\u6253\u4e2d\u6587\u55ce", "urls": [], "replies": {"first": [], "last": [], "noMoreReplies": true}, "images": [], "id": 73368645}, {"postBy": {"location": "\u53f0\u7063", "utc": 1507567291000, "level": 0, "avatar": "http://filestoresg1.beetalkmobile.com:8081/file/3150053557025168254", "name": "\ud83c\udf39"}, "content": "\u751a\u9ebc\ud83c\udf6c\uff1f", "urls": [], "replies": {"first": [], "last": [], "noMoreReplies": true}, "images": [], "id": 73568501}]}
