{"noMoreComments": true, "cursorEnd": 0, "id": "6605415", "comments": [{"postBy": {"location": "", "utc": 1505057825000, "level": 0, "avatar": "http://filestoresg1.beetalkmobile.com:8081/file/182522248564469804", "name": "\u7fd2\u6163"}, "content": "\u4ed6\u53ea\u662f\u77ed\u66ab\u505c\u7559\u5728\u60a8\u751f\u547d\u4e2d<br />\u4f46\u60a8\u662f\u4ed6\u7684\u4e00\u8f29\u5b50<br />\u597d\u597d\u611b\u4ed6<br />\u771f\u5fc3\u7684\u22ef", "urls": [], "replies": {"first": [], "last": [], "noMoreReplies": true}, "images": [], "id": 71693832}, {"postBy": {"location": "\u53f0\u4e2d\u5e02\u00b7\u53f0\u7063", "utc": 1505372131000, "level": 0, "avatar": "http://filestoresg1.beetalkmobile.com:8081/file/-36455398502700287", "name": "\u72c4\u723a\ud83d\udc8b"}, "content": "\u6211\u5bb6\u7684\ud83d\ude02", "urls": [], "replies": {"first": [{"content": "\u5bb6\u88e1\u5982\u679c\u6709\u5176\u4ed6\u8c93\uff0c\u8981\u8a18\u5f97\u9694\u96e2\u4e00\u9031\u5594\uff0c\u9023\u7528\u5177 \u6c34\u90fd\u8981\u5fb9\u5e95\u9694\u96e2", "reply": "", "id": 48384543, "name": "\u6210\u529f\u4f54\u9818\u59b3"}], "last": [], "noMoreReplies": true}, "images": ["http://filestoresg1.beetalkmobile.com:8081/file/6f0178fb3576a48a5b7276d716a51699"], "id": 71892490}, {"postBy": {"location": "\u53f0\u7063", "utc": 1505386942000, "level": 0, "avatar": "http://filestoresg1.beetalkmobile.com:8081/file/4751077706243142116", "name": "\u975c"}, "content": "\u68c4\u990a\u7684\u662f\u738b\u516b", "urls": [], "replies": {"first": [], "last": [], "noMoreReplies": true}, "images": [], "id": 71903728}, {"postBy": {"location": "\u65b0\u5317\u5e02\u00b7\u53f0\u7063", "utc": 1505397616000, "level": 0, "avatar": "http://filestoresg1.beetalkmobile.com:8081/file/4961513235940207927", "name": "\ud83d\ude1d\u2661\u73a5\u51dc\u2661\ud83d\ude1d"}, "content": "\u6211\u4e5f\u6709\u64bf\u5230\u4e00\u96bb\u8c93\u54aa\u73fe\u5728\u6709\u9577\u6bd4\u8f03\u5927\u4e86\uff0c\u800c\u4e14\u9084\u5f88\u8de9\ud83d\ude02\ud83d\ude02", "urls": [], "replies": {"first": [], "last": [], "noMoreReplies": true}, "images": ["http://filestoresg1.beetalkmobile.com:8081/file/f5efe597a8d468d8a7ec7179d433b57c", "http://filestoresg1.beetalkmobile.com:8081/file/13129e09bcb7bb96c173dd9ca71eccbf"], "id": 71913540}]}
