{"noMoreComments": true, "cursorEnd": 0, "id": "6617789", "comments": [{"postBy": {"location": "\u53f0\u5317\u5e02\u00b7\u53f0\u7063", "utc": 1505229543000, "level": 0, "avatar": "http://filestoresg1.beetalkmobile.com:8081/file/6242904978874195235", "name": "Nimo"}, "content": "\u4e00\u516c\u65a4\u7684\u808c\u8089\u597d\u96e3\u554a\uff5e\uff5e\ud83d\ude02", "urls": [], "replies": {"first": [{"content": "\u5c0d\u5440\u6211\u4e5f\u662f\u5f88\u96e3", "reply": "", "id": 48330266, "name": "\u725b\u2650\ufe0f\u5065\u8eab\u7537\u5b69"}], "last": [], "noMoreReplies": true}, "images": [], "id": 71805565}, {"postBy": {"location": "", "utc": 1505230865000, "level": 0, "avatar": "http://filestoresg1.beetalkmobile.com:8081/file/-928810225545063363", "name": "(X_X)"}, "content": "\u4e0d\u6b62\u96e3\u7df4...\u88dc\u5145\u54c1\u9084\u5f88\u71d2\u9322...\ud83d\ude2d", "urls": [], "replies": {"first": [{"content": "\u4e00\u5929\u8981\u5403\u591a\u5c11\u5440...\uff1f", "reply": "", "id": 48971782, "name": "Aaron W. "}], "last": [], "noMoreReplies": true}, "images": [], "id": 71806937}, {"postBy": {"location": "\u53f0\u7063", "utc": 1505269011000, "level": 0, "avatar": "http://filestoresg1.beetalkmobile.com:8081/file/-6387840393544070259", "name": "Mr.L"}, "content": "\u62dc\u4e00\u4e0b \u5f88\u731b ", "urls": [], "replies": {"first": [], "last": [], "noMoreReplies": true}, "images": [], "id": 71824346}, {"postBy": {"location": "\u53f0\u5357\u5e02\u00b7\u53f0\u7063", "utc": 1505270317000, "level": 0, "avatar": "http://filestoresg1.beetalkmobile.com:8081/file/-1429278236868753179", "name": "\u4e0d"}, "content": "\u611f\u540c\u8eab\u53d7", "urls": [], "replies": {"first": [], "last": [], "noMoreReplies": true}, "images": [], "id": 71825141}, {"postBy": {"location": "\u65b0\u5317\u5e02\u00b7\u53f0\u7063", "utc": 1505299655000, "level": 0, "avatar": "http://filestoresg1.beetalkmobile.com:8081/file/-5027257418167023865", "name": "S"}, "content": "\u883b\u725b\u87f2\u86f9\ud83d\ude06<br />\u4f60\u7684\u9ad4\u614b\u5df2\u7d93\u5c4c\u6253\u7248\u4e0a\u5f88\u591a\u4eba\u4e86\uff0c\u6709\u4e9b\u8ddf\u4f60\u4e00\u6a23\u7df4\u5169\u4e09\u5e74\u4e86\u9084\u662f\u505c\u7559\u5728\u539f\u5730\uff01<br />\u52a0\u6cb9\uff01\u66ff\u53f0\u7063\u722d\u53d6\u672a\u4f86\u7684PRO CARD\u3002", "urls": [], "replies": {"first": [], "last": [], "noMoreReplies": true}, "images": [], "id": 71845094}, {"postBy": {"location": "\u53f0\u5317\u5e02\u00b7\u53f0\u7063", "utc": 1506696326000, "level": 0, "avatar": "http://filestoresg1.beetalkmobile.com:8081/file/923465537301679367", "name": "\u51f9\u5305"}, "content": "\u98f2\u98df\u5230\u5e95\u8981\u600e\u63a7\u5236.....", "urls": [], "replies": {"first": [], "last": [], "noMoreReplies": true}, "images": [], "id": 72858174}, {"postBy": {"location": "Taipei City\u00b7Taiwan", "utc": 1506699109000, "level": 0, "avatar": "http://filestoresg1.beetalkmobile.com:8081/file/8355238343324260948", "name": "Aaron W. "}, "content": "\u5f37\uff01<br /><br />\u6bcf\u5929\u7df42\u5c0f\u6642..\uff1f", "urls": [], "replies": {"first": [], "last": [], "noMoreReplies": true}, "images": [], "id": 72861762}, {"postBy": {"location": "\u65b0\u5317\u5e02\u00b7\u53f0\u7063", "utc": 1512147592000, "level": 0, "avatar": "http://filestoresg1.beetalkmobile.com:8081/file/3918711136693039665", "name": "\u5e03\u9b6f\u65af\u674e"}, "content": "\u4e2d\u80af", "urls": [], "replies": {"first": [], "last": [], "noMoreReplies": true}, "images": [], "id": 76898187}, {"postBy": {"location": "Taoyuan City\u00b7Taiwan", "utc": 1512166573000, "level": 0, "avatar": "http://filestoresg1.beetalkmobile.com:8081/file/6632411392262519915", "name": "Shawn"}, "content": "\u771f\u7684\uff0c\u627e\u5230\u9069\u5408\u81ea\u5df1\u7684\u76ee\u6a19\u53ca\u8a13\u7df4\u65b9\u5f0f\u5f88\u91cd\u8981", "urls": [], "replies": {"first": [], "last": [], "noMoreReplies": true}, "images": [], "id": 76906776}, {"postBy": {"location": "\u65b0\u5317\u5e02\u00b7\u53f0\u7063", "utc": 1512170854000, "level": 0, "avatar": "http://filestoresg1.beetalkmobile.com:8081/file/5460135162243416577", "name": "Han\u5357\u804a"}, "content": "\u8a72\u4e0d\u6703\u5ee3\u798f\u6d3e\u51fa\u6240\u65c1\u7684\u5065\u5de5==", "urls": [], "replies": {"first": [], "last": [], "noMoreReplies": true}, "images": [], "id": 76908620}, {"postBy": {"location": "", "utc": 1512313571000, "level": 0, "avatar": "http://filestoresg1.beetalkmobile.com:8081/file/5922921809137635337", "name": "\u5c0f\u96e8"}, "content": "\u8acb\u554f\u600e\u9ebc\u5403\u600e\u9ebc\u904b\u52d5", "urls": [], "replies": {"first": [], "last": [], "noMoreReplies": true}, "images": [], "id": 77019848}, {"postBy": {"location": "\u53f0\u5317\u5e02\u00b7\u53f0\u7063", "utc": 1512315892000, "level": 0, "avatar": "http://filestoresg1.beetalkmobile.com:8081/file/-4221006443051594527", "name": "\u674e\u5c0f\u5b89"}, "content": "\u7df410\u5e74\u4ee5\u4e0a\u55ce\uff1f\u68d2\u68d2^^", "urls": [], "replies": {"first": [], "last": [], "noMoreReplies": true}, "images": [], "id": 77022624}, {"postBy": {"location": "\u9ad8\u96c4\u5e02\u00b7\u53f0\u7063", "utc": 1512378474000, "level": 0, "avatar": "http://filestoresg1.beetalkmobile.com:8081/file/-4172405833198644721", "name": "\u963f\u8ce2"}, "content": "\u6211\u4e5f\u662f\u52aa\u529b\ud83d\udcaa\ud83c\udffd\u4e2d", "urls": [], "replies": {"first": [], "last": [], "noMoreReplies": true}, "images": [], "id": 77063674}, {"postBy": {"location": "\u9ad8\u96c4\u5e02\u00b7\u53f0\u7063", "utc": 1512503605000, "level": 0, "avatar": "http://filestoresg1.beetalkmobile.com:8081/file/-1741203100219067380", "name": "\u8521\u5976\u8336"}, "content": "\u7537\u795e\uff0c\uff0c\uff0c\u54c7\u9019\u500b\u808c\u8089\u53b2\u5bb3\u4e86!", "urls": [], "replies": {"first": [], "last": [], "noMoreReplies": true}, "images": [], "id": 77165091}, {"postBy": {"location": "\u9ad8\u96c4\u5e02\u00b7\u53f0\u7063", "utc": 1512531209000, "level": 0, "avatar": "http://filestoresg1.beetalkmobile.com:8081/file/4415428691807867393", "name": "\u5049"}, "content": "\u5403\u771f\u7684\u5f88\u91cd\u8981\uff01\uff01", "urls": [], "replies": {"first": [], "last": [], "noMoreReplies": true}, "images": [], "id": 77178859}]}
