{"noMoreComments": false, "cursorEnd": 25, "id": "6160898", "comments": [{"postBy": {"location": "\u6843\u5712\u5e02\u00b7\u53f0\u7063", "utc": 1498474209000, "level": 0, "avatar": "http://filestoresg1.beetalkmobile.com:8081/file/8732466488481007942", "name": "\ud83d\udc3e\u6c6a\u6c6a\ud83d\udc36\ud83d\udc3e"}, "content": "\u4e0d\u662f\u4e00\u5806\u597d\u53cb\u9080\u8acb<br /><br />\u53ca\u9109\u6c11\u7d04\u59b3\u51fa\u9580\u4e86", "urls": [], "replies": {"first": [], "last": [], "noMoreReplies": true}, "images": [], "id": 67370718}, {"postBy": {"location": "\u6843\u5712\u5e02\u00b7\u53f0\u7063", "utc": 1498477231000, "level": 0, "avatar": "http://filestoresg1.beetalkmobile.com:8081/file/8363426401807235328", "name": "\u5747\ud83d\udc7e"}, "content": "\ud83d\udc4b\ud83d\udc4b\ud83d\udc4b", "urls": [], "replies": {"first": [], "last": [], "noMoreReplies": true}, "images": [], "id": 67372786}, {"postBy": {"location": "\u6843\u5712\u5e02\u00b7\u53f0\u7063", "utc": 1498507103000, "level": 0, "avatar": "http://filestoresg1.beetalkmobile.com:8081/file/-1953606760726809600", "name": "\u9b3c..."}, "content": "\u4f86\u5427 \u9078\u6211\u9078\u6211\u9078\u6211\ud83d\ude04\ud83d\ude04\ud83d\ude04\ud83d\ude04", "urls": [], "replies": {"first": [], "last": [], "noMoreReplies": true}, "images": [], "id": 67395491}, {"postBy": {"location": "\u65b0\u7af9\u7e23\u00b7\u53f0\u7063", "utc": 1498533422000, "level": 0, "avatar": "http://filestoresg1.beetalkmobile.com:8081/file/6351947945104644068", "name": "\u60f3\u7a69\u5b9a\u3002"}, "content": "\u55e8\u55e8", "urls": [], "replies": {"first": [], "last": [], "noMoreReplies": true}, "images": [], "id": 67405577}, {"postBy": {"location": "\u65b0\u7af9\u5e02\u00b7\u53f0\u7063", "utc": 1498559179000, "level": 0, "avatar": "http://filestoresg1.beetalkmobile.com:8081/file/-6264630206584942306", "name": "\u7121\u804a\u4f86\u804a"}, "content": "\u53ef\u4ee5\u8a8d\u8b58\u4e0d\u6b621\u4e0b\u55ce", "urls": [], "replies": {"first": [], "last": [], "noMoreReplies": true}, "images": [], "id": 67422442}, {"postBy": {"location": "\u53f0\u5317\u5e02\u00b7\u53f0\u7063", "utc": 1498578719000, "level": 0, "avatar": "http://filestoresg1.beetalkmobile.com:8081/file/-4454698842817895911", "name": "Chris"}, "content": "\u5f88\u908a\u7de3\u4f46\u4e0d\u662f\u4f4f\u6843\u5712\u7684\u4eba\uff0c<br />\u60f3\u77ad\u89e3\u4ec0\u9ebc\u662f\u649e\u69b4\u69e4", "urls": [], "replies": {"first": [{"content": "\u9592\u6643\u7684\u53f0\u8a9e \u650f\u310c\u3127\u3129 \u310c\u3127\u3122", "reply": "", "id": 45408990, "name": "\ud83d\ude08\u4e2d\u58e2\u5927\u60e1\u9b54\u26a1\u96f7\u8499\u26a1"}], "last": [], "noMoreReplies": true}, "images": [], "id": 67439731}, {"postBy": {"location": "\u6843\u5712\u5e02\u00b7\u53f0\u7063", "utc": 1498629512000, "level": 0, "avatar": "http://filestoresg1.beetalkmobile.com:8081/file/-1657381836240423195", "name": "\ud83d\ude08\u4e2d\u58e2\u5927\u60e1\u9b54\u26a1\u96f7\u8499\u26a1"}, "content": "\u6211\u6bd4\u8f03\u64d4\u5fc3\u59b3\u662f\u88ab\u69b4\u69e4\u649e", "urls": [], "replies": {"first": [], "last": [], "noMoreReplies": true}, "images": [], "id": 67465409}, {"postBy": {"location": "\u65b0\u7af9\u7e23\u00b7\u53f0\u7063", "utc": 1498637512000, "level": 0, "avatar": "http://filestoresg1.beetalkmobile.com:8081/file/6351947945104644068", "name": "\u60f3\u7a69\u5b9a\u3002"}, "content": "\u55e8\u55e8", "urls": [], "replies": {"first": [], "last": [], "noMoreReplies": true}, "images": [], "id": 67470875}, {"postBy": {"location": "\u6843\u5712\u5e02\u00b7\u53f0\u7063", "utc": 1498646658000, "level": 0, "avatar": "http://filestoresg1.beetalkmobile.com:8081/file/4514178046226811088", "name": "\u4fca\u54e5"}, "content": "\u8a8d\u8b58\u53bb\u6253\u649e\u7403\u5427\uff5e", "urls": [], "replies": {"first": [], "last": [], "noMoreReplies": true}, "images": [], "id": 67477647}, {"postBy": {"location": "\u6843\u5712\u5e02\u00b7\u53f0\u7063", "utc": 1498668419000, "level": 0, "avatar": "http://filestoresg1.beetalkmobile.com:8081/file/4613137375430546674", "name": "Hsiang"}, "content": "\u649e\u69b4\u69e4\u662f\u90a3\u62db\uff1f", "urls": [], "replies": {"first": [], "last": [], "noMoreReplies": true}, "images": [], "id": 67497970}, {"postBy": {"location": "\u6843\u5712\u5e02\u00b7\u53f0\u7063", "utc": 1498669071000, "level": 0, "avatar": "http://filestoresg1.beetalkmobile.com:8081/file/-6519682818276953001", "name": "\u5e78\u798f-\u5982\u5c65\u8584\u51b0"}, "content": "+1\u5566@@", "urls": [], "replies": {"first": [], "last": [], "noMoreReplies": true}, "images": [], "id": 67498438}, {"postBy": {"location": "\u6843\u5712\u5e02\u00b7\u53f0\u7063", "utc": 1498669896000, "level": 0, "avatar": "http://filestoresg1.beetalkmobile.com:8081/file/-1867281883354456063", "name": "\u827e\u6d1b\u65af"}, "content": "\u6843\u5712++", "urls": [], "replies": {"first": [], "last": [], "noMoreReplies": true}, "images": [], "id": 67498991}, {"postBy": {"location": "\u6843\u5712\u5e02\u00b7\u53f0\u7063", "utc": 1498682422000, "level": 0, "avatar": "http://filestoresg1.beetalkmobile.com:8081/file/5348511646224379921", "name": "Ryder"}, "content": "\u55e8\u7f8e\u5973<br />\u59b3\u662f\u7f8e\u5230\u6c92\u670b\u53cb\u5427\uff1f<br />\u5b85\u54e5+1", "urls": [], "replies": {"first": [], "last": [], "noMoreReplies": true}, "images": [], "id": 67503850}, {"postBy": {"location": "Taoyuan City\u00b7Taiwan", "utc": 1498697822000, "level": 0, "avatar": "http://filestoresg1.beetalkmobile.com:8081/file/-2823213803067988104", "name": "\u5c37\u5c2c\u2026"}, "content": "\u69b4\u69e4\u2026\u81ed\u81ed\u7684\u2026", "urls": [], "replies": {"first": [], "last": [], "noMoreReplies": true}, "images": [], "id": 67509248}, {"postBy": {"location": "\u6843\u5712\u5e02\u00b7\u53f0\u7063", "utc": 1498714241000, "level": 0, "avatar": "http://filestoresg1.beetalkmobile.com:8081/file/8512868745398705411", "name": "bs"}, "content": "\u6211\u4e5f\u8981\u4e00\u8d77\u73a9", "urls": [], "replies": {"first": [], "last": [], "noMoreReplies": true}, "images": [], "id": 67519435}, {"postBy": {"location": "\u65b0\u7af9\u7e23\u00b7\u53f0\u7063", "utc": 1499415380000, "level": 0, "avatar": "http://filestoresg1.beetalkmobile.com:8081/file/3549087217852150786", "name": "\u9ad8\u5cf0\u884c\u5211\u8005"}, "content": "\u6211\u8d85\u51fa\u908a\u7de3\u5730\u5e36\u600e\u9ebc\u7b97", "urls": [], "replies": {"first": [], "last": [], "noMoreReplies": true}, "images": [], "id": 67973775}, {"postBy": {"location": "\u65b0\u7af9\u7e23\u00b7\u53f0\u7063", "utc": 1499433692000, "level": 0, "avatar": "http://filestoresg1.beetalkmobile.com:8081/file/-3915135483930106785", "name": "\u832b\u832b\u7136"}, "content": "\u4e00\u8d77\u560d", "urls": [], "replies": {"first": [], "last": [], "noMoreReplies": true}, "images": [], "id": 67988196}, {"postBy": {"location": "\u65b0\u7af9\u7e23\u00b7\u53f0\u7063", "utc": 1499556963000, "level": 0, "avatar": "http://filestoresg1.beetalkmobile.com:8081/file/-3915135483930106785", "name": "\u832b\u832b\u7136"}, "content": "@@<br />", "urls": [], "replies": {"first": [], "last": [], "noMoreReplies": true}, "images": ["http://filestoresg1.beetalkmobile.com:8081/file/8e622f3b4f51ba1525c1909e528ce0dd"], "id": 68068583}, {"postBy": {"location": "\u6843\u5712\u5e02\u00b7\u53f0\u7063", "utc": 1499643200000, "level": 0, "avatar": "http://filestoresg1.beetalkmobile.com:8081/file/-8592153404589568584", "name": "\u8521\u6607\u9d3b"}, "content": "\u53ef\u4ee5\u8a8d\u8b58\u4ea4\u670b\u53cb\u804a\u804a\u55ce", "urls": [], "replies": {"first": [], "last": [], "noMoreReplies": true}, "images": [], "id": 68129583}]}
