{"noMoreComments": false, "cursorEnd": 25, "id": "6612972", "comments": [{"postBy": {"location": "\u9ad8\u96c4\u5e02\u00b7\u53f0\u7063", "utc": 1505211913000, "level": 0, "avatar": "http://filestoresg1.beetalkmobile.com:8081/file/4251597083277240934", "name": "\u5c0f\u4e0d\u9ede147\u2764\u2764"}, "content": "chenioi", "urls": [], "replies": {"first": [], "last": [], "noMoreReplies": true}, "images": [], "id": 71788745}, {"postBy": {"location": "\u65b0\u5317\u5e02\u00b7\u53f0\u7063", "utc": 1505223413000, "level": 0, "avatar": "http://filestoresg1.beetalkmobile.com:8081/file/-5666029686428543362", "name": "\ud83c\udf6d\ud83c\udf6d"}, "content": "0932050206", "urls": [], "replies": {"first": [], "last": [], "noMoreReplies": true}, "images": [], "id": 71798629}, {"postBy": {"location": "\u65b0\u5317\u5e02\u00b7\u53f0\u7063", "utc": 1505264403000, "level": 0, "avatar": "http://filestoresg1.beetalkmobile.com:8081/file/2", "name": "User blocked"}, "content": "\u6211\u6211\u6211\ud83d\ude02\ud83d\ude02\ud83d\ude02", "urls": [], "replies": {"first": [], "last": [], "noMoreReplies": true}, "images": [], "id": 71821679}, {"postBy": {"location": "\u53f0\u4e2d\u5e02\u00b7\u53f0\u7063", "utc": 1520901446000, "level": 0, "avatar": "http://filestoresg1.beetalkmobile.com:8081/file/-7511263106481415680", "name": "\u5e79\u8a71\u738b"}, "content": "a19991124", "urls": [], "replies": {"first": [], "last": [], "noMoreReplies": true}, "images": [], "id": 83558469}, {"postBy": {"location": "\u53f0\u7063", "utc": 1520903903000, "level": 0, "avatar": "http://filestoresg1.beetalkmobile.com:8081/file/5913284608644829204", "name": "\u9ed8\u5440"}, "content": "0936245504", "urls": [], "replies": {"first": [], "last": [], "noMoreReplies": true}, "images": [], "id": 83560237}, {"postBy": {"location": "", "utc": 1520904473000, "level": 0, "avatar": "http://filestoresg1.beetalkmobile.com:8081/file/1871054333211644637", "name": "\u61a8\u3124"}, "content": "phoenix01032017", "urls": [], "replies": {"first": [], "last": [], "noMoreReplies": true}, "images": [], "id": 83560677}, {"postBy": {"location": "\u6843\u5712\u5e02\u00b7\u53f0\u7063", "utc": 1520910391000, "level": 0, "avatar": "http://filestoresg1.beetalkmobile.com:8081/file/-4264803292720183537", "name": "\u963f\u5442\u5442"}, "content": "a01933", "urls": [], "replies": {"first": [], "last": [], "noMoreReplies": true}, "images": [], "id": 83565401}, {"postBy": {"location": "\u53f0\u4e2d\u5e02\u00b7\u53f0\u7063", "utc": 1520925991000, "level": 0, "avatar": "http://filestoresg1.beetalkmobile.com:8081/file/1327640520495783091", "name": "\u5f26\u6a02"}, "content": "\u6211\u53ef\u4ee5\u52a0\u5165\u55ce\uff1f   \u54c8\u54c8\ud83d\ude02\ud83d\ude02", "urls": [], "replies": {"first": [], "last": [], "noMoreReplies": true}, "images": [], "id": 83578941}, {"postBy": {"location": "\u9ad8\u96c4\u5e02\u00b7\u53f0\u7063", "utc": 1520979733000, "level": 0, "avatar": "http://filestoresg1.beetalkmobile.com:8081/file/4766755662815379410", "name": "\u859b\u6749\u6749\u2122\ud83c\udf39\ud83c\udf39"}, "content": "hert33", "urls": [], "replies": {"first": [], "last": [], "noMoreReplies": true}, "images": [], "id": 83626876}, {"postBy": {"location": "\u9ad8\u96c4\u5e02\u00b7\u53f0\u7063", "utc": 1521020994000, "level": 0, "avatar": "http://filestoresg1.beetalkmobile.com:8081/file/-563245700934846334", "name": "R"}, "content": "0983278221", "urls": [], "replies": {"first": [], "last": [], "noMoreReplies": true}, "images": [], "id": 83660182}, {"postBy": {"location": "\u53f0\u7063", "utc": 1521040456000, "level": 0, "avatar": "http://filestoresg1.beetalkmobile.com:8081/file/1764668908033701314", "name": "\u9baa\u9b5a"}, "content": "hb313013hb", "urls": [], "replies": {"first": [], "last": [], "noMoreReplies": true}, "images": [], "id": 83681097}, {"postBy": {"location": "\u65b0\u5317\u5e02\u00b7\u53f0\u7063", "utc": 1521082449000, "level": 0, "avatar": "http://filestoresg1.beetalkmobile.com:8081/file/-2969941433786407166", "name": "\u5c0f\u5b89"}, "content": "0930760858", "urls": [], "replies": {"first": [], "last": [], "noMoreReplies": true}, "images": [], "id": 83710729}, {"postBy": {"location": "\u6843\u5712\u5e02\u00b7\u53f0\u7063", "utc": 1521305497000, "level": 0, "avatar": "http://filestoresg1.beetalkmobile.com:8081/file/7596541230851328135", "name": "\u7a4e\u5152"}, "content": "jullyking ", "urls": [], "replies": {"first": [], "last": [], "noMoreReplies": true}, "images": [], "id": 83905218}, {"postBy": {"location": "\u65b0\u5317\u5e02\u00b7\u53f0\u7063", "utc": 1521305873000, "level": 0, "avatar": "http://filestoresg1.beetalkmobile.com:8081/file/4594971266082148417", "name": "Wu Ning"}, "content": "lwn_1012", "urls": [], "replies": {"first": [], "last": [], "noMoreReplies": true}, "images": [], "id": 83905638}, {"postBy": {"location": "\u53f0\u5317\u5e02\u00b7\u53f0\u7063", "utc": 1521333580000, "level": 0, "avatar": "http://filestoresg1.beetalkmobile.com:8081/file/2844769754672438439", "name": "\u807d\u8aaa\u6211\u53eb\u591a\u591a\u8c6c"}, "content": "0926113629", "urls": [], "replies": {"first": [], "last": [], "noMoreReplies": true}, "images": [], "id": 83923082}, {"postBy": {"location": "", "utc": 1521345035000, "level": 0, "avatar": "http://filestoresg1.beetalkmobile.com:8081/file/-4799906991632552447", "name": "\u96ef\u96ef"}, "content": "likelike891103", "urls": [], "replies": {"first": [], "last": [], "noMoreReplies": true}, "images": [], "id": 83932434}, {"postBy": {"location": "\u53f0\u7063", "utc": 1521350573000, "level": 0, "avatar": "http://filestoresg1.beetalkmobile.com:8081/file/-492022642692173068", "name": "Jie"}, "content": "25932802", "urls": [], "replies": {"first": [], "last": [], "noMoreReplies": true}, "images": [], "id": 83937263}, {"postBy": {"location": "\u53f0\u5317\u5e02\u00b7\u53f0\u7063", "utc": 1521468104000, "level": 0, "avatar": "http://filestoresg1.beetalkmobile.com:8081/file/2388079882820778199", "name": "HS_\u6728\u5e0c"}, "content": "renny00313", "urls": [], "replies": {"first": [], "last": [], "noMoreReplies": true}, "images": [], "id": 84038785}, {"postBy": {"location": "", "utc": 1521469781000, "level": 0, "avatar": "http://filestoresg1.beetalkmobile.com:8081/file/-4799906991632552447", "name": "\u96ef\u96ef"}, "content": "likelike891103", "urls": [], "replies": {"first": [], "last": [], "noMoreReplies": true}, "images": [], "id": 84041123}]}
