{"noMoreComments": false, "cursorEnd": 21, "id": "6840140", "comments": [{"postBy": {"location": "\u65b0\u5317\u5e02\u00b7\u53f0\u7063", "utc": 1508185844000, "level": 0, "avatar": "http://filestoresg1.beetalkmobile.com:8081/file/5946383203260570266", "name": "\u5c1a\u672a\u8a2d\u7f6e"}, "content": "\u4f60\u662f\u5687\u4e0d\u5230\u6211\u7684", "urls": [], "replies": {"first": [], "last": [], "noMoreReplies": true}, "images": [], "id": 74038351}, {"postBy": {"location": "\u6843\u5712\u5e02\u00b7\u53f0\u7063", "utc": 1508188386000, "level": 0, "avatar": "http://filestoresg1.beetalkmobile.com:8081/file/1849139986294191316", "name": "\u5c0f\u6649"}, "content": "\u54c8\u56c9\u5f88\u9ad8\u8208\u8a8d\u8b58\u4f60!\u8acb\u554f\u53ef\u4ee5\u6210\u70ba\u597d\u53cb\u55ce", "urls": [], "replies": {"first": [], "last": [], "noMoreReplies": true}, "images": [], "id": 74039408}, {"postBy": {"location": "\u53f0\u7063", "utc": 1508193073000, "level": 0, "avatar": "http://filestoresg1.beetalkmobile.com:8081/file/-7395862744292799834", "name": "\u7121\u76f8\u662f\u7a7a"}, "content": "\u4ffa\u7d55\u5c0d\u4e0d\u6703\u8aaa\u4ffa\u9583\u5c3f\u60f9 \u2026\u2026\u5471\u5471", "urls": [], "replies": {"first": [], "last": [], "noMoreReplies": true}, "images": [], "id": 74041096}, {"postBy": {"location": "\u53f0\u7063", "utc": 1508195748000, "level": 0, "avatar": "http://filestoresg1.beetalkmobile.com:8081/file/6648592902492097215", "name": "akira"}, "content": "\u6703\u5728\u88e1\u9762\u5077\u5c3f\u5c3f\u55ce", "urls": [], "replies": {"first": [], "last": [], "noMoreReplies": true}, "images": [], "id": 74042340}, {"postBy": {"location": "\u53f0\u7063", "utc": 1508199200000, "level": 0, "avatar": "http://filestoresg1.beetalkmobile.com:8081/file/6395098281561616408", "name": "Tomorrow"}, "content": "\u525b\u6436\u5b8c\u9280\u884c\uff1f", "urls": [], "replies": {"first": [], "last": [], "noMoreReplies": true}, "images": [], "id": 74044291}, {"postBy": {"location": "\u53f0\u4e2d\u5e02\u00b7\u53f0\u7063", "utc": 1508222248000, "level": 0, "avatar": "http://filestoresg1.beetalkmobile.com:8081/file/2042219710382870857", "name": "\u5c0f\u9b5a\u5152"}, "content": "\u9019\u5929\u6c23\uff0c\u5c31\u662f\u6eab\u6cc9\u5929\u3002\u3002", "urls": [], "replies": {"first": [], "last": [], "noMoreReplies": true}, "images": [], "id": 74063494}, {"postBy": {"location": "Taoyuan City\u00b7Taiwan", "utc": 1508222724000, "level": 0, "avatar": "http://filestoresg1.beetalkmobile.com:8081/file/6632411392262519915", "name": "Shawn"}, "content": "\u9019\u662f\u79c1\u4eba\u6d74\u6c60\u5427", "urls": [], "replies": {"first": [], "last": [], "noMoreReplies": true}, "images": [], "id": 74063902}, {"postBy": {"location": "\u65b0\u5317\u5e02\u00b7\u53f0\u7063", "utc": 1508223548000, "level": 0, "avatar": "http://filestoresg1.beetalkmobile.com:8081/file/1321784506759328840", "name": "\u6137"}, "content": "\u90a3\u662f\u50b3\u8aaa\u4e2d\u7684\u9ed1\u9ebb\u9ebb\u706b\u5c71\u6ce5\u9762\u819c\u55ce\uff1f\ud83d\ude32\ud83d\ude32\ud83d\ude32\ud83d\ude32", "urls": [], "replies": {"first": [], "last": [], "noMoreReplies": true}, "images": [], "id": 74064632}, {"postBy": {"location": "\u53f0\u7063", "utc": 1508246804000, "level": 0, "avatar": "http://filestoresg1.beetalkmobile.com:8081/file/-6331148458496907767", "name": "\u5c0f\u660e"}, "content": "\u6211\u53d7\u9a5a\u4e86", "urls": [], "replies": {"first": [], "last": [], "noMoreReplies": true}, "images": [], "id": 74086747}, {"postBy": {"location": "\u53f0\u5317\u5e02\u00b7\u53f0\u7063", "utc": 1508248242000, "level": 0, "avatar": "http://filestoresg1.beetalkmobile.com:8081/file/-1231512392617550466", "name": "\u99ac\u514b\u767d"}, "content": "\u5305\u5927\u4eba\uff0c\u59b3\u984d\u982d\u4e0a\u7684\u6708\u4eae\u600e\u9ebc\u4e0d\u898b\u4e86", "urls": [], "replies": {"first": [], "last": [], "noMoreReplies": true}, "images": [], "id": 74088528}, {"postBy": {"location": "\u65b0\u5317\u5e02\u00b7\u53f0\u7063", "utc": 1508296148000, "level": 0, "avatar": "http://filestoresg1.beetalkmobile.com:8081/file/3722004109692662331", "name": "\u5468\u5149\u5149"}, "content": "\u8f9b\u82e6\u4e86!", "urls": [], "replies": {"first": [], "last": [], "noMoreReplies": true}, "images": [], "id": 74122546}, {"postBy": {"location": "", "utc": 1508418994000, "level": 0, "avatar": "http://filestoresg1.beetalkmobile.com:8081/file/3990008951504651588", "name": "\u60f3\u8981"}, "content": "\u4f60\u58be\u4e01?", "urls": [], "replies": {"first": [], "last": [], "noMoreReplies": true}, "images": [], "id": 74228292}, {"postBy": {"location": "\u53f0\u5357\u5e02\u00b7\u53f0\u7063", "utc": 1508420573000, "level": 0, "avatar": "http://filestoresg1.beetalkmobile.com:8081/file/5998605601507837175", "name": "\u9673\u6e05\u6c60"}, "content": "\u62b1\u8457\u6211\u7761\u6700\u597d\u02d9", "urls": [], "replies": {"first": [], "last": [], "noMoreReplies": true}, "images": [], "id": 74230224}, {"postBy": {"location": "\u65b0\u5317\u5e02\u00b7\u53f0\u7063", "utc": 1508512130000, "level": 0, "avatar": "http://filestoresg1.beetalkmobile.com:8081/file/-3680659147400906005", "name": "\u7c21\u55ae\u7684\u8a8d\u8b58"}, "content": "\u59b3\u597d \u621128\u6b72 \u8eab\u9ad8178 \u80fd\u6a5f\u6703\u8a8d\u8b58\u59b3\u55ce \u5e0c\u671b\u80fd\u53ef\u5403\u500b\u98ef\u8a8d\u8b58 \u6216\u662f\u4e00\u8d77\u770b\u96fb\u5f71 \u8aa0\u5fc3\u8ffd\u6c42", "urls": [], "replies": {"first": [], "last": [], "noMoreReplies": true}, "images": [], "id": 74305454}, {"postBy": {"location": "\u53f0\u5357\u5e02\u00b7\u53f0\u7063", "utc": 1508625393000, "level": 0, "avatar": "http://filestoresg1.beetalkmobile.com:8081/file/5998605601507837175", "name": "\u9673\u6e05\u6c60"}, "content": "\u4e0d\u5316\u599d\u4e5f\u662f\u7f8e\u02d9", "urls": [], "replies": {"first": [], "last": [], "noMoreReplies": true}, "images": [], "id": 74392389}, {"postBy": {"location": "\u53f0\u7063", "utc": 1508636836000, "level": 0, "avatar": "http://filestoresg1.beetalkmobile.com:8081/file/4906407918343283464", "name": "\u6708"}, "content": "\u908a\u6ce1\u908a\u6577\u6bd4\u8f03\u597d\u5438\u6536\u55ce\uff1f\uff01", "urls": [], "replies": {"first": [], "last": [], "noMoreReplies": true}, "images": [], "id": 74399445}, {"postBy": {"location": "\u6843\u5712\u5e02\u00b7\u53f0\u7063", "utc": 1508672780000, "level": 0, "avatar": "http://filestoresg1.beetalkmobile.com:8081/file/8246614287508130304", "name": "Red wing"}, "content": "\u9019\u662f\u65e5\u672c\u9762\u819c\u55ce\uff1f\ud83e\udd23\ud83e\udd23\ud83e\udd23", "urls": [], "replies": {"first": [], "last": [], "noMoreReplies": true}, "images": [], "id": 74431121}, {"postBy": {"location": "\u65b0\u5317\u5e02\u00b7\u53f0\u7063", "utc": 1509384910000, "level": 0, "avatar": "http://filestoresg1.beetalkmobile.com:8081/file/1653235583726072842", "name": "\u557e\u7f8a"}, "content": "\u518d\u5f80\u4e0b\u62cd", "urls": [], "replies": {"first": [], "last": [], "noMoreReplies": true}, "images": [], "id": 74869242}, {"postBy": {"location": "\u53f0\u5317\u5e02\u00b7\u53f0\u7063", "utc": 1509396599000, "level": 0, "avatar": "http://filestoresg1.beetalkmobile.com:8081/file/-1231512392617550466", "name": "\u99ac\u514b\u767d"}, "content": "\u7a81\u7136\u6709\u7a2e\u5305\u9f8d\u661f\u7684fu", "urls": [], "replies": {"first": [], "last": [], "noMoreReplies": true}, "images": [], "id": 74875183}]}
