{"noMoreComments": false, "cursorEnd": 21, "id": "6404689", "comments": [{"postBy": {"location": "\u53f0\u4e2d\u5e02\u00b7\u53f0\u7063", "utc": 1502109442000, "level": 0, "avatar": "http://filestoresg1.beetalkmobile.com:8081/file/9044441935739571113", "name": "\u611b\u60c5\u5931\u6557\u8005"}, "content": "\u55ae\u8eab\u53ea\u662f\u904e\u7a0b\uff0c\u4eba\u7e3d\u6703\u6709\u55ae\u8eab\u7684\u6642\u5019\uff0c\u59b3\u4e5f\u5f88\u5feb\u812b\u96e2\u4e86", "urls": [], "replies": {"first": [], "last": [], "noMoreReplies": true}, "images": [], "id": 69787416}, {"postBy": {"location": "\u53f0\u4e2d\u5e02\u00b7\u53f0\u7063", "utc": 1502109776000, "level": 0, "avatar": "http://filestoresg1.beetalkmobile.com:8081/file/7085255133170553606", "name": "\u5091"}, "content": "\u6c92\u4eba\u60f3\u55ae\u8eab\u554a \u54c8\u54c8\ud83d\ude2d\ud83d\ude2d", "urls": [], "replies": {"first": [], "last": [], "noMoreReplies": true}, "images": [], "id": 69787738}, {"postBy": {"location": "\u53f0\u4e2d\u5e02\u00b7\u53f0\u7063", "utc": 1502109891000, "level": 0, "avatar": "http://filestoresg1.beetalkmobile.com:8081/file/-2342653554556496124", "name": "Yagami"}, "content": "\u5509\u3002", "urls": [], "replies": {"first": [], "last": [], "noMoreReplies": true}, "images": [], "id": 69787876}, {"postBy": {"location": "\u9ad8\u96c4\u5e02\u00b7\u53f0\u7063", "utc": 1502109926000, "level": 0, "avatar": "http://filestoresg1.beetalkmobile.com:8081/file/7393212951286246991", "name": "\u5f35\u5c11\u8ed2"}, "content": "\u4f60\u597d\u5440", "urls": [], "replies": {"first": [], "last": [], "noMoreReplies": true}, "images": [], "id": 69787923}, {"postBy": {"location": "\u65b0\u7af9\u5e02\u00b7\u53f0\u7063", "utc": 1502109965000, "level": 0, "avatar": "http://filestoresg1.beetalkmobile.com:8081/file/-2364606388831014656", "name": "\u4e11\u5d8b\u99a8"}, "content": "\u4f86\u5427\uff01", "urls": [], "replies": {"first": [], "last": [], "noMoreReplies": true}, "images": [], "id": 69787963}, {"postBy": {"location": "\u53f0\u7063", "utc": 1502109974000, "level": 0, "avatar": "http://filestoresg1.beetalkmobile.com:8081/file/-909779892378697612", "name": "\u660e"}, "content": "\u59b3\u597d\u554a~\u4e00\u8d77\u7d42\u7d50\u55ae\u8eab\u55ce", "urls": [], "replies": {"first": [], "last": [], "noMoreReplies": true}, "images": [], "id": 69787966}, {"postBy": {"location": "\u53f0\u4e2d\u5e02\u00b7\u53f0\u7063", "utc": 1502110415000, "level": 0, "avatar": "http://filestoresg1.beetalkmobile.com:8081/file/-6759411536886362504", "name": "\u9a19\u4eba\u5e03"}, "content": "\u627e\u6211\u5427", "urls": [], "replies": {"first": [], "last": [], "noMoreReplies": true}, "images": [], "id": 69788408}, {"postBy": {"location": "\u53f0\u4e2d\u5e02\u00b7\u53f0\u7063", "utc": 1502110861000, "level": 0, "avatar": "http://filestoresg1.beetalkmobile.com:8081/file/-2076807039321359615", "name": "\u8d99\u80b2\u8fb0"}, "content": "\u6211\u5011\u4f86\u804a\u804a\ud83d\ude02", "urls": [], "replies": {"first": [], "last": [], "noMoreReplies": true}, "images": [], "id": 69788873}, {"postBy": {"location": "\u5c4f\u6771\u7e23\u00b7\u53f0\u7063", "utc": 1502110912000, "level": 0, "avatar": "http://filestoresg1.beetalkmobile.com:8081/file/-266566697514218822", "name": "\u5e7d\u9748"}, "content": "\u592a\u6311\u5427", "urls": [], "replies": {"first": [], "last": [], "noMoreReplies": true}, "images": [], "id": 69788931}, {"postBy": {"location": "", "utc": 1502111448000, "level": 0, "avatar": "http://filestoresg1.beetalkmobile.com:8081/file/-6000699054159341553", "name": "\u7159\u6d88\u96f2\u6563\uff5e\u32a3\u6d41\u6c13\u8ce4\u5154\u32a3"}, "content": "\u61c9\u8a72\u5f88\u5c11\u4eba\u60f3\u55ae\u8eab\u5427\uff1f", "urls": [], "replies": {"first": [], "last": [], "noMoreReplies": true}, "images": [], "id": 69789470}, {"postBy": {"location": "\u5b9c\u862d\u7e23\u00b7\u53f0\u7063", "utc": 1502112697000, "level": 0, "avatar": "http://filestoresg1.beetalkmobile.com:8081/file/-3725954618821501278", "name": "\u963f\u5112"}, "content": "\u55ae\u8eab\u6bd4\u8f03\u6709\u9322\u554a \u591a\u597d~", "urls": [], "replies": {"first": [], "last": [], "noMoreReplies": true}, "images": [], "id": 69790725}, {"postBy": {"location": "", "utc": 1502113339000, "level": 0, "avatar": "http://filestoresg1.beetalkmobile.com:8081/file/3138819847452668425", "name": "\ud83e\udd81\ufe0f\u7562"}, "content": "\u63a8\u85a6\uff1a\u5c0f\u6625\u5b50<br />ID:babylove7157", "urls": [], "replies": {"first": [], "last": [], "noMoreReplies": true}, "images": [], "id": 69791403}, {"postBy": {"location": "\u9ad8\u96c4\u5e02\u00b7\u53f0\u7063", "utc": 1502113508000, "level": 0, "avatar": "http://filestoresg1.beetalkmobile.com:8081/file/-3602854402163230324", "name": "\u5341\u500d\u5049\u5927\u7684\u9280\u8272\u602a\u7269"}, "content": "\u53ea\u662f\u4f86\u5831\u540d\u7684\u90fd\u6158\u4e0d\u5fcd\u7779<br />\u5e6b\u59b3\u63a5\u4e0b\u4e00\u53e5\u4e86(\u2299_\u2299)/", "urls": [], "replies": {"first": [], "last": [], "noMoreReplies": true}, "images": [], "id": 69791591}, {"postBy": {"location": "\u53f0\u5357\u5e02\u00b7\u53f0\u7063", "utc": 1502115458000, "level": 0, "avatar": "http://filestoresg1.beetalkmobile.com:8081/file/8032255698344640782", "name": "\u727d\u624b\u7684 \u5e78\u798f"}, "content": "\u61c9\u8a72\u662f\u4f60\u8981\u6c42\u592a\u591a\u5427\uff01", "urls": [], "replies": {"first": [], "last": [], "noMoreReplies": true}, "images": [], "id": 69793830}, {"postBy": {"location": "\u53f0\u4e2d\u5e02\u00b7\u53f0\u7063", "utc": 1502116351000, "level": 0, "avatar": "http://filestoresg1.beetalkmobile.com:8081/file/4098636319975556369", "name": "Min\ud83d\udc63"}, "content": "\u54c8\u54c8", "urls": [], "replies": {"first": [], "last": [], "noMoreReplies": true}, "images": [], "id": 69794820}, {"postBy": {"location": "\u65b0\u5317\u5e02\u00b7\u53f0\u7063", "utc": 1502116514000, "level": 0, "avatar": "http://filestoresg1.beetalkmobile.com:8081/file/-8260567074151768215", "name": "\u4e0d\u7701\u4eba\u4e8b"}, "content": "\ud83d\ude02\ud83d\ude02\ud83d\ude02", "urls": [], "replies": {"first": [], "last": [], "noMoreReplies": true}, "images": [], "id": 69795009}, {"postBy": {"location": "\u65b0\u5317\u5e02\u00b7\u53f0\u7063", "utc": 1502117893000, "level": 0, "avatar": "http://filestoresg1.beetalkmobile.com:8081/file/-7114859470579677864", "name": "apsida"}, "content": "\u55ae\u8eab\u6709\u6642\u771f\u7684\u597d\u5b64\u55ae\u5bc2\u5bde\u89ba\u5f97\u51b7", "urls": [], "replies": {"first": [], "last": [], "noMoreReplies": true}, "images": [], "id": 69796508}, {"postBy": {"location": "\u53f0\u5317\u5e02\u00b7\u53f0\u7063", "utc": 1502118350000, "level": 0, "avatar": "http://filestoresg1.beetalkmobile.com:8081/file/-8042873679176386560", "name": "\u7aa9\u5c45\u7537"}, "content": "\u4e0d\u8981\u6015\u4f86\u966a\u6211<br /><br /><br /><br />\u4e00\u8d77\u62bd\u4e94\u661f\u554a\uff01\uff01", "urls": [], "replies": {"first": [], "last": [], "noMoreReplies": true}, "images": ["http://filestoresg1.beetalkmobile.com:8081/file/e07f43e40eebd1c14bac33e9ae2ef8d9"], "id": 69797049}, {"postBy": {"location": "\u5f70\u5316\u7e23\u00b7\u53f0\u7063", "utc": 1502120198000, "level": 0, "avatar": "http://filestoresg1.beetalkmobile.com:8081/file/7838533859508554643", "name": "\u5d06\u516b\u5d06\u5d06"}, "content": "\u55e8\uff01", "urls": [], "replies": {"first": [], "last": [], "noMoreReplies": true}, "images": [], "id": 69799127}]}
