{"noMoreComments": true, "cursorEnd": 0, "id": "6231347", "comments": [{"postBy": {"location": "\u9ad8\u96c4\u5e02\u00b7\u53f0\u7063", "utc": 1499606186000, "level": 0, "avatar": "http://filestoresg1.beetalkmobile.com:8081/file/1630557057886825729", "name": "\u5c0f\u67cf"}, "content": "\u6709\u7a7a\u767c\u6587\u9084\u4e0d\u8d95\u5feb\u53bb\u5e6b\u8c93\u7687\u6376\u80cc", "urls": [], "replies": {"first": [{"content": "\u662f\u7684 \u5974\u5a62\u6b63\u53bb\u6376\u6376\ud83d\udc31\ud83d\udc31", "reply": "", "id": 45848164, "name": "\u777f\u5152"}], "last": [], "noMoreReplies": true}, "images": [], "id": 68105550}]}
