{"noMoreComments": true, "cursorEnd": 0, "id": "6163373", "comments": [{"postBy": {"location": "\u4e2d\u56fd", "utc": 1498506561000, "level": 0, "avatar": "http://filestoresg1.beetalkmobile.com:8081/file/-4266992402575744499", "name": "\u592a\u79e4\u51e1"}, "content": "\u6490\u4e0b\u53bb\uff0c\u4e0b\u4e00\u500b127\u5929\u7b49\u8457\u4f60\uff0c\u52a0\u6cb9\u3002", "urls": [], "replies": {"first": [{"content": "\u67d0\u500b\u5c64\u9762\u8a72\u8ddf\u4f60\u8aaa\u500b\u8b1d\u8b1d", "reply": "", "id": 45365305, "name": "\u8449\u5927\u5ef7"}], "last": [], "noMoreReplies": true}, "images": [], "id": 67395341}, {"postBy": {"location": "\u53f0\u5317\u5e02\u00b7\u53f0\u7063", "utc": 1498575527000, "level": 0, "avatar": "http://filestoresg1.beetalkmobile.com:8081/file/-4454698842817895911", "name": "Chris"}, "content": "\u5225\u96e3\u904e\uff0c\u4eca\u5929\u5df2\u7d93128\u4e86", "urls": [], "replies": {"first": [{"content": "\u8b1d\u8b1d\u4f60\u8ddf\u6211\u8a18\u5f97\u4e00\u6a23\u6e05\u695a", "reply": "", "id": 45399107, "name": "\u8449\u5927\u5ef7"}], "last": [], "noMoreReplies": true}, "images": [], "id": 67436451}]}
