{"noMoreComments": false, "cursorEnd": 24, "id": "6778379", "comments": [{"postBy": {"location": "", "utc": 1507441538000, "level": 0, "avatar": "http://filestoresg1.beetalkmobile.com:8081/file/4683539108175509761", "name": "Lenii\ud83d\udc8b\u4e0d\u8981\u52a0\u6211\u9664\u975e\u4f60\u5f88\u5e25"}, "content": "\u88dc<br />\u770b\u4f86\u9019\u6a13\u6211\u53ea\u80fd\u81ea\u5df1\u84cb\u4e86....", "urls": [], "replies": {"first": [{"content": "\u54c8\uff0c\u9577\u9aee\u7537\u751f\u53f0\u7063\u61c9\u8a72\u6bd4\u8f03\u5c11\u5594", "reply": "", "id": 49270915, "name": "\u58eb\u5ead"}], "last": [{"content": "\u8981\u4e0d\u8981\u6539\u9020\u6211(\u8aa4)\n\u4eba\u9020\u4eba\u7684\u6982\u5ff5", "reply": "", "id": 49341385, "name": "\u58eb\u5ead"}, {"content": "\u60f3\u7559\u9577\u982d\u9aee\ud83d\ude01\u4f46\u662f\u6211\u4e0d\u6703\u6574\u7406\u982d\u9aee\u6240\u4ee5\ud83d\ude02", "reply": "", "id": 51479788, "name": "\u9716"}], "noMoreReplies": false}, "images": ["http://filestoresg1.beetalkmobile.com:8081/file/61bff5749f6db1308ff1c366da0b76dc", "http://filestoresg1.beetalkmobile.com:8081/file/4aeb2b2b0b9e70ade0030e75c9fa1226", "http://filestoresg1.beetalkmobile.com:8081/file/76d167c685cc172e6c3c9cb2462f9e3d", "http://filestoresg1.beetalkmobile.com:8081/file/4dd1ead38dd2ceaacd6624ab49c94c25"], "id": 73460846}, {"postBy": {"location": "\u65b0\u5317\u5e02\u00b7\u53f0\u7063", "utc": 1507467648000, "level": 0, "avatar": "http://filestoresg1.beetalkmobile.com:8081/file/2998336346414778321", "name": "\u8def\u514b"}, "content": "\u77ed\u9aee\u55ae\u773c\u76ae \u54c8\u54c8", "urls": [], "replies": {"first": [], "last": [], "noMoreReplies": true}, "images": [], "id": 73482968}, {"postBy": {"location": "\u65b0\u5317\u5e02\u00b7\u53f0\u7063", "utc": 1507797952000, "level": 0, "avatar": "http://filestoresg1.beetalkmobile.com:8081/file/5136435641064953600", "name": "S"}, "content": "\u8996\u89ba\u7cfb", "urls": [], "replies": {"first": [], "last": [], "noMoreReplies": true}, "images": [], "id": 73759670}, {"postBy": {"location": "\u53f0\u7063", "utc": 1507800330000, "level": 0, "avatar": "http://filestoresg1.beetalkmobile.com:8081/file/2917723445950849570", "name": "Reger(\u0e51\u02c3\u0335\u1d17\u02c2\u0335)\u0648"}, "content": "\u90a3\u963f\u8b2c\u4e00\u5b9a\u662f\u59b3\u7684\u8d85\u7d1a\u5929\u83dc\u4e86<br />\u81c9\u66f8\u9084\u883b\u6709\u540d\u7684\u651d\u5f71\u5e2b\uff1a\u8b2c\u5ddd\u7533", "urls": [], "replies": {"first": [{"content": "\u8d85\u6709\u540d\ud83d\ude31\ud83d\ude31", "reply": "", "id": 53005079, "name": "Lenii\ud83d\udc8b\u4e0d\u8981\u52a0\u6211\u9664\u975e\u4f60\u5f88\u5e25"}], "last": [], "noMoreReplies": true}, "images": [], "id": 73761896}, {"postBy": {"location": "\u65b0\u5317\u5e02\u00b7\u53f0\u7063", "utc": 1508614163000, "level": 0, "avatar": "http://filestoresg1.beetalkmobile.com:8081/file/2210297899200341248", "name": "\u96d9\u9b5a\u5ea7"}, "content": "\u771f\u5fc3\u60f3\u505a\u670b\u53cb\u53ef\u4ee5\u7559Line\u55ce", "urls": [], "replies": {"first": [], "last": [], "noMoreReplies": true}, "images": ["http://filestoresg1.beetalkmobile.com:8081/file/93220c3568d81058ee2109443a9e4322"], "id": 74388365}, {"postBy": {"location": "\u65b0\u5317\u5e02\u00b7\u53f0\u7063", "utc": 1509442062000, "level": 0, "avatar": "http://filestoresg1.beetalkmobile.com:8081/file/4482152559949462528", "name": "So"}, "content": "\u578b\u52d5\u56f0\u7537\u8def\u904e\ud83d\ude02\ud83d\ude02", "urls": [], "replies": {"first": [], "last": [], "noMoreReplies": true}, "images": ["http://filestoresg1.beetalkmobile.com:8081/file/24b871f7eda08b194927268846baae72", "http://filestoresg1.beetalkmobile.com:8081/file/bcfb7042236fc1fb2fc8cacd408518b8"], "id": 74904251}, {"postBy": {"location": "", "utc": 1511203849000, "level": 0, "avatar": "http://filestoresg1.beetalkmobile.com:8081/file/6068873199249668609", "name": "Jonny3Tear"}, "content": "\u9001\u59b3\u4e0d\u7528\u8b1d\ud83d\udc4c", "urls": [], "replies": {"first": [{"content": "\u539f\u672c\u6709\u8ffd\u4ed6IG \u4f46\u662f\u5f8c\u4f86\u767c\u73fe\u4ed6\u592aman\u5c31\u9000\u8ffd\u4e86\ud83d\ude02", "reply": "", "id": 53005088, "name": "Lenii\ud83d\udc8b\u4e0d\u8981\u52a0\u6211\u9664\u975e\u4f60\u5f88\u5e25"}], "last": [], "noMoreReplies": true}, "images": ["http://filestoresg1.beetalkmobile.com:8081/file/02d989bac9563e99621a05301f90356b"], "id": 76228044}, {"postBy": {"location": "", "utc": 1511249027000, "level": 0, "avatar": "http://filestoresg1.beetalkmobile.com:8081/file/6804161706077191939", "name": "\u306a\u304a\u5948\u7dd2"}, "content": "\u65e5\u7cfb\u3001\u8996\u89ba\u7cfb\u3001\u97d3\u7cfb\u7684\u9020\u578b\u90fd\u4e0d\u932f\uff01", "urls": [], "replies": {"first": [{"content": "\u4e2d\u9593\u7684\u90a3\u500b\ud83d\ude0d", "reply": "", "id": 53005091, "name": "Lenii\ud83d\udc8b\u4e0d\u8981\u52a0\u6211\u9664\u975e\u4f60\u5f88\u5e25"}, {"content": "\u3046\u3093\u3001\u30a4\u30b1\u30e1\u30f3\u3067\u3059\u306d", "reply": "Lenii\ud83d\udc8b\u4e0d\u8981\u52a0\u6211\u9664\u975e\u4f60\u5f88\u5e25", "id": 53012158, "name": "\u306a\u304a\u5948\u7dd2"}], "last": [], "noMoreReplies": true}, "images": ["http://filestoresg1.beetalkmobile.com:8081/file/87251e3449f9f08a1373dc9c0157aad8", "http://filestoresg1.beetalkmobile.com:8081/file/0553982e953217ffb25a3832f1c8d0fa", "http://filestoresg1.beetalkmobile.com:8081/file/247652287b76ab8e45b485e7c25198af"], "id": 76255371}, {"postBy": {"location": "\u53f0\u4e2d\u5e02\u00b7\u53f0\u7063", "utc": 1513149451000, "level": 0, "avatar": "http://filestoresg1.beetalkmobile.com:8081/file/8944244518625819140", "name": "\ud83d\udca4"}, "content": "\u4e0d\u65e9\u8aaa \u6211\u526a\u6389\u4e86\ud83d\ude02", "urls": [], "replies": {"first": [{"content": "\u4ec0\u9ebc\u6642\u5019\u7559\u56de\u4f86", "reply": "", "id": 53005097, "name": "Lenii\ud83d\udc8b\u4e0d\u8981\u52a0\u6211\u9664\u975e\u4f60\u5f88\u5e25"}], "last": [], "noMoreReplies": true}, "images": [], "id": 77632916}, {"postBy": {"location": "\u9ad8\u96c4\u5e02\u00b7\u53f0\u7063", "utc": 1513218731000, "level": 0, "avatar": "http://filestoresg1.beetalkmobile.com:8081/file/3126142461619185690", "name": "\u82bd\u82bd\ud83c\udf77"}, "content": "\u597d\u5c4c\u54e6", "urls": [], "replies": {"first": [{"content": "\u7f8e\u5973\u597d\u6b63\ud83d\ude0d\u96d6\u7136\u770b\u5230\u7389\u862d\u82b1\u6211\u4e0d\u722d\u6c23\u7684\u7b11\u4e86\u4e00\u4e0b", "reply": "", "id": 53005103, "name": "Lenii\ud83d\udc8b\u4e0d\u8981\u52a0\u6211\u9664\u975e\u4f60\u5f88\u5e25"}], "last": [], "noMoreReplies": true}, "images": [], "id": 77681904}, {"postBy": {"location": "", "utc": 1517345928000, "level": 0, "avatar": "http://filestoresg1.beetalkmobile.com:8081/file/4683539108175509761", "name": "Lenii\ud83d\udc8b\u4e0d\u8981\u52a0\u6211\u9664\u975e\u4f60\u5f88\u5e25"}, "content": "\u88dc", "urls": [], "replies": {"first": [], "last": [], "noMoreReplies": true}, "images": ["http://filestoresg1.beetalkmobile.com:8081/file/afd071c59043c0869ea0aec78c0a8409", "http://filestoresg1.beetalkmobile.com:8081/file/b081ecaed4341a8cd4c247a751e6cf63", "http://filestoresg1.beetalkmobile.com:8081/file/eb13b2b784cc1ac1e2ab1f393d41182a", "http://filestoresg1.beetalkmobile.com:8081/file/93622c9dacbb1598bfe95ff788197ae9"], "id": 80779795}, {"postBy": {"location": "\u53f0\u5317\u5e02\u00b7\u53f0\u7063", "utc": 1517369975000, "level": 0, "avatar": "http://filestoresg1.beetalkmobile.com:8081/file/-6292763421537878694", "name": "\u5a1c\u5a1c\ud83d\udc8b"}, "content": "\u9577\u9aee\u7537\uff0c\u771f\u7684\u8981\u642d\u5916\u578b<br />\u4e0d\u7136\u59b3\u770b\u5916\u9762\u54ea\u500b\u6d41\u6d6a\u6f22\u662f\u77ed\u9aee\u7684\uff1f", "urls": [], "replies": {"first": [{"content": "\u4f46\u662f\u6b50\u7f8e\u570b\u5bb6\u7684\u6d41\u6d6a\u6f22\u771f\u7684\u5f88\u6709\u578b\ud83d\ude48", "reply": "", "id": 55077979, "name": "Lenii\ud83d\udc8b\u4e0d\u8981\u52a0\u6211\u9664\u975e\u4f60\u5f88\u5e25"}], "last": [], "noMoreReplies": true}, "images": [], "id": 80793293}, {"postBy": {"location": "New Taipei City\u00b7Taiwan", "utc": 1517374069000, "level": 0, "avatar": "http://filestoresg1.beetalkmobile.com:8081/file/4466580177647752704", "name": "Sven"}, "content": "\u6211\u9577\u9aee\uff08\u73fe\u5728\u9084\u4e0d\u5920\u9577\u5427\uff09\u4f46\u662f\u55ae\u773c\u76ae \u54c8\u54c8\u54c8 \u5225\u770b\u6211\u7684\u7167\u7247\u90fd\u662f\u597d\u5e7e\u5e74\u524d\u7684\u4e86\uff0c\u73fe\u5728\u771f\u7684\u7559\u9577\u9aee\u52a0\u9b0d\u5b50\u54c8\u54c8\u54c8", "urls": [], "replies": {"first": [], "last": [], "noMoreReplies": true}, "images": [], "id": 80796402}, {"postBy": {"location": "", "utc": 1517418015000, "level": 0, "avatar": "http://filestoresg1.beetalkmobile.com:8081/file/4014681996648289282", "name": "\u6591\u6591ig angel90187"}, "content": "\u8209\u624b", "urls": [], "replies": {"first": [{"content": "\u64ca\u638c\u270b", "reply": "", "id": 55077986, "name": "Lenii\ud83d\udc8b\u4e0d\u8981\u52a0\u6211\u9664\u975e\u4f60\u5f88\u5e25"}, {"content": "\ud83d\ude1dgive me five", "reply": "", "id": 55860394, "name": "\u6591\u6591ig angel90187"}], "last": [], "noMoreReplies": true}, "images": [], "id": 80837209}, {"postBy": {"location": "\u6843\u5712\u5e02\u00b7\u53f0\u7063", "utc": 1521401915000, "level": 0, "avatar": "http://filestoresg1.beetalkmobile.com:8081/file/6924506552086745116", "name": "\u706b\u5c71\u54e5"}, "content": "\u4e86\u89e3\uff0c\u4e86\u89e3\uff0c\u5bc2\u5bde\u96e3\u8010\uff0c\u5bc2\u5bde\u96e3\u8010\uff0c\u54c8\u54c8~\u7a7a\u6d1e\u611f", "urls": [], "replies": {"first": [], "last": [], "noMoreReplies": true}, "images": [], "id": 83987985}, {"postBy": {"location": "\u65b0\u5317\u5e02\u00b7\u53f0\u7063", "utc": 1521431121000, "level": 0, "avatar": "http://filestoresg1.beetalkmobile.com:8081/file/-7403493362337653504", "name": "\u09e1\u09e2\u09e2\u0361\u035c\ud83d\udc2c\u09e2\u0361\u035c\u96ea\u6a47"}, "content": "\u6b0a\u529b\u904a\u6232\u88e1\u9762\uff5e\u9f8d\u5973\u7684\u8001\u516c\u4e5f\u5728\ud83d\ude02\ud83d\ude02", "urls": [], "replies": {"first": [{"content": "\u82e6\u7b49\u7b2c\u516b\u5b63\u4e2d......", "reply": "", "id": 55077988, "name": "Lenii\ud83d\udc8b\u4e0d\u8981\u52a0\u6211\u9664\u975e\u4f60\u5f88\u5e25"}, {"content": "\u6211\u4e5f\u5728\u7b49\ud83d\ude02\ud83d\ude02", "reply": "", "id": 55082754, "name": "\u09e1\u09e2\u09e2\u0361\u035c\ud83d\udc2c\u09e2\u0361\u035c\u96ea\u6a47"}], "last": [], "noMoreReplies": true}, "images": [], "id": 84004443}, {"postBy": {"location": "", "utc": 1522932478000, "level": 0, "avatar": "http://filestoresg1.beetalkmobile.com:8081/file/1767092231847718151", "name": "Sylvia"}, "content": "\u6211\u627e\u5230\u540c\u597d\u4e86\uff01\u539fpo\u6162\u7528", "urls": [], "replies": {"first": [{"content": "\u54e6\u6211\u7684\u5929\u554a \u5b8c\u5b8c\u5168\u5168\u662f\u6211\u7684\u83dc\ud83d\ude2d\u6a13\u4e3b\u4e00\u751f\u5e73\u5b89\ud83d\ude4f\ud83c\udffb", "reply": "", "id": 55077989, "name": "Lenii\ud83d\udc8b\u4e0d\u8981\u52a0\u6211\u9664\u975e\u4f60\u5f88\u5e25"}], "last": [], "noMoreReplies": true}, "images": ["http://filestoresg1.beetalkmobile.com:8081/file/99796c022a761110d047e713dac9d6f3", "http://filestoresg1.beetalkmobile.com:8081/file/6cce1d337ecc5b17689744ee30158518", "http://filestoresg1.beetalkmobile.com:8081/file/1d34a6f9ff6f98fef50d4d124a15477e", "http://filestoresg1.beetalkmobile.com:8081/file/156d1556b745b830b1ceea3bcf1e9b29", "http://filestoresg1.beetalkmobile.com:8081/file/ba3fb3579487b1e11514d6b82e9a149f", "http://filestoresg1.beetalkmobile.com:8081/file/da657da9859ed74690c8864204a62781"], "id": 85285123}, {"postBy": {"location": "\u53f0\u7063", "utc": 1522934719000, "level": 0, "avatar": "http://filestoresg1.beetalkmobile.com:8081/file/-4957966192941031416", "name": "\u9673\u5e8f"}, "content": "\u7ffb\u4e86\u4e00\u4e0b\u4ee5\u524d\u7684\u982d\u9aee\uff0c\u6211\u9084\u662f\u6bd4\u8f03\u60f3\u7559\u56de\u9577\u9aee\u5440\uff01\u597d\u4e45\u56c9", "urls": [], "replies": {"first": [{"content": "\u9577\u9aee\u5f88\u6709\u578b\ud83d\ude48", "reply": "", "id": 55077998, "name": "Lenii\ud83d\udc8b\u4e0d\u8981\u52a0\u6211\u9664\u975e\u4f60\u5f88\u5e25"}, {"content": "\u8b1d\u8b1d", "reply": "", "id": 55094554, "name": "\u9673\u5e8f"}], "last": [], "noMoreReplies": true}, "images": ["http://filestoresg1.beetalkmobile.com:8081/file/743c83ec043d625afc780c9f7401df31", "http://filestoresg1.beetalkmobile.com:8081/file/24d550bb7d3e17635f77e880fbaf9562", "http://filestoresg1.beetalkmobile.com:8081/file/72841da7d9a43b14e2eafede764bf0f4", "http://filestoresg1.beetalkmobile.com:8081/file/bb679f1276ab2044e12f6c5604ebf700", "http://filestoresg1.beetalkmobile.com:8081/file/a023a5ed2144dd6cb79da225b0c599d1", "http://filestoresg1.beetalkmobile.com:8081/file/24f81ba97c989cec014b72e5fbb2842c"], "id": 85288265}, {"postBy": {"location": "", "utc": 1522968017000, "level": 0, "avatar": "http://filestoresg1.beetalkmobile.com:8081/file/4683539108175509761", "name": "Lenii\ud83d\udc8b\u4e0d\u8981\u52a0\u6211\u9664\u975e\u4f60\u5f88\u5e25"}, "content": "\u88dc<br /><br />\u6700\u8fd1\u6c92\u770b\u5230\u4ec0\u9ebc\u9577\u9aee\u578b\u7537<br />\u6240\u4ee5\u88dc\u5716\u5f88\u6162", "urls": [], "replies": {"first": [{"content": "\u767d\u9aee\u7684\u662f\u8ab0\u5440 \u597d\u5e25\ud83d\ude0d\ud83d\ude0d\ud83d\ude0d", "reply": "", "id": 55315943, "name": "\u9ede\u8fea "}], "last": [], "noMoreReplies": true}, "images": ["http://filestoresg1.beetalkmobile.com:8081/file/5711d23383d41988d2194d5e4517fae1", "http://filestoresg1.beetalkmobile.com:8081/file/1c0d83d57490e5bbafa59948f6b346c1", "http://filestoresg1.beetalkmobile.com:8081/file/7fa365f963cf7c96e607443c8cc06b02", "http://filestoresg1.beetalkmobile.com:8081/file/1471456428d1465941b09d72b0fda209", "http://filestoresg1.beetalkmobile.com:8081/file/d17e2e7cd4c230fc316c01697fac3f5a"], "id": 85320299}]}
