{"noMoreComments": true, "cursorEnd": 0, "id": "6447496", "comments": [{"postBy": {"location": "", "utc": 1502733779000, "level": 0, "avatar": "http://filestoresg1.beetalkmobile.com:8081/file/4926511387779910673", "name": "\ud83c\udf3bJanet\ud83d\udc33"}, "content": "\u6211\u4e5f\u5728\u8ffd\u90192\u90e8\ud83d\ude09\ud83d\ude09", "urls": [], "replies": {"first": [], "last": [], "noMoreReplies": true}, "images": [], "id": 70197142}, {"postBy": {"location": "\u53f0\u5317\u5e02\u00b7\u53f0\u7063", "utc": 1502758751000, "level": 0, "avatar": "http://filestoresg1.beetalkmobile.com:8081/file/-2098853346845845317", "name": "\ud83d\udc37\ud83d\udc11"}, "content": "\u7b2c22\u5e74\u597d\u597d\u5947\u6703\u8ddf\u97d3\u570b\u7248\u672c\u6709\u4f55\u4e0d\u540c", "urls": [], "replies": {"first": [{"content": "\u807d\u8aaa\u597d\u50cf\u6709\u6539\u7de8", "reply": "", "id": 47240533, "name": "\u5687\u5230\u5403\u624b\u624b\ud83d\ude4b\ud83c\udffb\u200d\u2642\ufe0f"}], "last": [{"content": "\u4f46\u770b\u904e\u4e86\u539f\u7248\u7684\u6703\u6015\u6c92\u65b0\u6897", "reply": "\ud83d\udc37\ud83d\udc11", "id": 47275452, "name": "\u5687\u5230\u5403\u624b\u624b\ud83d\ude4b\ud83c\udffb\u200d\u2642\ufe0f"}, {"content": "\u5c0d\u554a\uff0c\u6211\u4e0a\u500b\u6708\u624d\u770b\u4e86\u97d3\u570b\u7248\ud83d\ude04", "reply": "\u5687\u5230\u5403\u624b\u624b\ud83d\ude4b\ud83c\udffb\u200d\u2642\ufe0f", "id": 47281929, "name": "\ud83d\udc37\ud83d\udc11"}], "noMoreReplies": false}, "images": [], "id": 70205839}, {"postBy": {"location": "\u53f0\u7063", "utc": 1502792726000, "level": 0, "avatar": "http://filestoresg1.beetalkmobile.com:8081/file/3289130761835397347", "name": "\u8ca2\u8ca2\u9999\ud83c\udf54"}, "content": "\u8ffd22\u5e74\u544a\u767d\uff0c\u5fc5\u770b", "urls": [], "replies": {"first": [], "last": [], "noMoreReplies": true}, "images": [], "id": 70229444}]}
