{"noMoreComments": true, "cursorEnd": 0, "id": "6083015", "comments": [{"postBy": {"location": "\u53f0\u5317\u5e02\u00b7\u53f0\u7063", "utc": 1497272218000, "level": 0, "avatar": "http://filestoresg1.beetalkmobile.com:8081/file/-4913470069212116476", "name": "Alan-Dai"}, "content": "\u6c92\u95dc\u4fc2\u3001\u6211\u5728\u4e4e\u59b3\u611f\u53d7\u5c31\u597d", "urls": [], "replies": {"first": [], "last": [], "noMoreReplies": true}, "images": [], "id": 66586997}, {"postBy": {"location": "\u5f70\u5316\u7e23\u00b7\u53f0\u7063", "utc": 1497272739000, "level": 0, "avatar": "http://filestoresg1.beetalkmobile.com:8081/file/3134812111169846458", "name": "\u53f0\u4e2d\u5c0f\u59da"}, "content": "\u4f69\u670d\uff0c\u771f\u5927\u7684\u6050\u61fc\u3002", "urls": [], "replies": {"first": [], "last": [], "noMoreReplies": true}, "images": [], "id": 66587505}, {"postBy": {"location": "\u57fa\u9686\u5e02\u00b7\u53f0\u7063", "utc": 1497272922000, "level": 0, "avatar": "http://filestoresg1.beetalkmobile.com:8081/file/4201370278092446015", "name": "\ud83d\udd95\u8f9c\u55ae\u6208\ud83d\udd95"}, "content": "\u5929\u554a\u5e74\u9f61\u548c\u7167\u7247\u597d\u9a19\u5594", "urls": [], "replies": {"first": [{"content": "\u4e2d\u80af\uff0c\u53ea\u80fd\u8aaa\u73fe\u5728\u71df\u990a\u592a\u597d\uff01", "reply": "", "id": 44830385, "name": "\ud83d\ude08\u591c\ud83d\ude08"}], "last": [], "noMoreReplies": true}, "images": [], "id": 66587674}, {"postBy": {"location": "Taipei City\u00b7Taiwan", "utc": 1497274050000, "level": 0, "avatar": "http://filestoresg1.beetalkmobile.com:8081/file/-7310315246543913243", "name": "\u8eca\u9593\u516d\u53eb"}, "content": "\u5c0f\u59b9\u59b9 \u662f\u8a72\u5237\u7259\u4e0a\u5e8a\u7761\u89ba\u4e86\u54e6\uff01", "urls": [], "replies": {"first": [], "last": [], "noMoreReplies": true}, "images": [], "id": 66588738}, {"postBy": {"location": "\u53f0\u5317\u5e02\u00b7\u53f0\u7063", "utc": 1497315572000, "level": 0, "avatar": "http://filestoresg1.beetalkmobile.com:8081/file/3279141702105475161", "name": "\u856d\u90ce"}, "content": "\u5e74\u8f15\u4eba\u7d42\u7a76\u662f\u5e74\u8f15\u4eba...", "urls": [], "replies": {"first": [], "last": [], "noMoreReplies": true}, "images": [], "id": 66615647}, {"postBy": {"location": "\u65b0\u7af9\u5e02\u00b7\u53f0\u7063", "utc": 1497317299000, "level": 0, "avatar": "http://filestoresg1.beetalkmobile.com:8081/file/4514178046226811088", "name": "\u4fca\u54e5"}, "content": "\u90a3\u4f55\u5fc5\u5728\u4e00\u8d77", "urls": [], "replies": {"first": [], "last": [], "noMoreReplies": true}, "images": [], "id": 66616561}, {"postBy": {"location": "\u82d7\u6817\u7e23\u00b7\u53f0\u7063", "utc": 1497319304000, "level": 0, "avatar": "http://filestoresg1.beetalkmobile.com:8081/file/-8443125598792393951", "name": "\u7b49\u5f85\u4e00\u500b\u4eba\u7684\u5496\u5561"}, "content": "\u5fc3\u4e0d\u5728<br />\u5f37\u6c42\u4e5f\u7121\u7528", "urls": [], "replies": {"first": [], "last": [], "noMoreReplies": true}, "images": [], "id": 66617760}]}
